flashlib/__init__.py
flashlib/flashlib.py
flashlib/utils.py
pwn_flashlib-0.201.dist-info/LICENSE
pwn_flashlib-0.201.dist-info/METADATA
pwn_flashlib-0.201.dist-info/WHEEL
pwn_flashlib-0.201.dist-info/top_level.txt
pwn_flashlib-0.201.dist-info/RECORD
