Metadata-Version: 2.1
Name: pwn-flashlib
Version: 0.201
Summary: A wrapper around pwntools but also with a few of the functions that I use on a daily basis.
Home-page: https://github.com/theflash2k/flashlib
Author: TheFlash2k
Author-email: alitaqi2000@gmail.com
License: UNKNOWN
Platform: UNKNOWN
Classifier: Programming Language :: Python :: 3
Classifier: License :: OSI Approved :: MIT License
Classifier: Operating System :: OS Independent
Requires-Python: >=3.6
License-File: LICENSE
Requires-Dist: pwntools
Requires-Dist: tqdm
